cli_presenter/__init__.py
cli_presenter/app.py
cli_presenter/ascii_renderer.py
cli_presenter/exporter.py
cli_presenter/main.py
cli_presenter/mermaid_parser.py
cli_presenter/parser.py
cli_presenter/templates/default.md
cli_presenter-0.1.0.dist-info/METADATA
cli_presenter-0.1.0.dist-info/WHEEL
cli_presenter-0.1.0.dist-info/entry_points.txt
cli_presenter-0.1.0.dist-info/RECORD
