Metadata-Version: 2.4
Name: cli-presenter
Version: 0.1.0
Summary: A terminal-based presentation tool.
Author-email: Alex Merced <alex@example.com>
Requires-Python: >=3.10
Requires-Dist: jinja2>=3.1.0
Requires-Dist: markdown>=3.4.0
Requires-Dist: pillow>=10.0.0
Requires-Dist: playwright>=1.40.0
Requires-Dist: textual>=0.40.0
Requires-Dist: typer>=0.9.0
Requires-Dist: weasyprint>=60.0
